sphinx_heigvd_theme/__init__.py
sphinx_heigvd_theme/domainindex.html
sphinx_heigvd_theme/genindex.html
sphinx_heigvd_theme/layout.html
sphinx_heigvd_theme/page.html
sphinx_heigvd_theme/search.html
sphinx_heigvd_theme/theme.conf
sphinx_heigvd_theme/static/app.css
sphinx_heigvd_theme/static/app.js
sphinx_heigvd_theme/static/chunk-vendors.js
sphinx_heigvd_theme/static/favicon.ico
sphinx_heigvd_theme/static/theme-vendors.js
sphinx_heigvd_theme/static/theme.css
sphinx_heigvd_theme/static/theme.js
sphinx_heigvd_theme/util/bodyheader.html
sphinx_heigvd_theme/util/extlinks.html
sphinx_heigvd_theme/util/footer.html
sphinx_heigvd_theme/util/linktags.html
sphinx_heigvd_theme/util/navbar.html
sphinx_heigvd_theme/util/navlinks.html
sphinx_heigvd_theme/util/pagenav.html
sphinx_heigvd_theme/util/searchbox.html
sphinx_heigvd_theme/util/sidetoc.html
sphinx_heigvd_theme-0.5.2.dist-info/AUTHORS
sphinx_heigvd_theme-0.5.2.dist-info/METADATA
sphinx_heigvd_theme-0.5.2.dist-info/WHEEL
sphinx_heigvd_theme-0.5.2.dist-info/entry_points.txt
sphinx_heigvd_theme-0.5.2.dist-info/top_level.txt
sphinx_heigvd_theme-0.5.2.dist-info/RECORD
