Metadata-Version: 2.1
Name: sphinx-heigvd-theme
Version: 0.5.2
Summary: A Sphinx-doc theme based on sphinx press theme
Home-page: https://github.com/heig-vd-tin/sphinx-heigvd-theme
Author: Yves Chevallier <yves.chevallier@heig-vd.ch>
License: MIT
Project-URL: Source, https://github.com/heig-vd-tin/sphinx-heigvd-theme
Project-URL: Tracker, https://github.com/heig-vd-tin/sphinx-heigvd-theme/issues
Keywords: sphinx doc theme heig-vd vue.js
Platform: UNKNOWN
Classifier: Framework :: Sphinx
Classifier: Framework :: Sphinx :: Theme
Classifier: Development Status :: 4 - Beta
Classifier: License :: OSI Approved :: MIT License
Classifier: Environment :: Console
Classifier: Environment :: Web Environment
Classifier: Intended Audience :: Developers
Classifier: Programming Language :: Python :: 3
Classifier: Programming Language :: Python :: 3.5
Classifier: Programming Language :: Python :: 3.6
Classifier: Programming Language :: Python :: 3.7
Classifier: Operating System :: OS Independent
Classifier: Topic :: Documentation
Classifier: Topic :: Software Development :: Documentation
Requires-Dist: sphinx (>=2.0.0)
